tableclone/__about__.py
tableclone/__init__.py
tableclone/cli_v2.py
tableclone/utils.py
tableclone/platforms/__init__.py
tableclone/platforms/abstracts.py
tableclone/platforms/airtable.py
tableclone/platforms/baserow.py
tableclone/platforms/bubble.py
tableclone/platforms/excel_file.py
tableclone/platforms/factory.py
tableclone/platforms/gdrive.py
tableclone/platforms/ksaar.py
tableclone/platforms/postgresql.py
tableclone/platforms/sqlite.py
tableclone/platforms/timetonic.py
tableclone/processing/sync.py
tableclone/tasking/abstract_task.py
tableclone/tasking/full_backup.py
tableclone/tasking/table_sync_task.py
tableclone-2.0.0.dist-info/METADATA
tableclone-2.0.0.dist-info/WHEEL
tableclone-2.0.0.dist-info/entry_points.txt
tableclone-2.0.0.dist-info/RECORD
