Metadata-Version: 2.4
Name: tableclone
Version: 2.0.0
Summary: Data synchronization tool for heterogeneous platforms (Airtable, Bubble, PostgreSQL, SQLite, Excel, etc.)
Author: Valérian LEBERT
License: MIT
Keywords: airtable,bubble,data,excel,postgresql,sqlite,sync
Classifier: Development Status :: 4 - Beta
Classifier: Intended Audience :: Developers
Classifier: Programming Language :: Python :: 3
Classifier: Programming Language :: Python :: 3.10
Classifier: Programming Language :: Python :: 3.11
Classifier: Programming Language :: Python :: 3.12
Requires-Python: >=3.10
Requires-Dist: bubbleio>=0.6.0
Requires-Dist: google-cloud-pubsub
Requires-Dist: gspread
Requires-Dist: oauth2client
Requires-Dist: openpyxl
Requires-Dist: pandas
Requires-Dist: psycopg2>=2.9.5
Requires-Dist: sqlalchemy>=1.4.46
Requires-Dist: xlsxwriter
Provides-Extra: dev
Requires-Dist: basedpyright; extra == 'dev'
Requires-Dist: pytest-cov>=4.1.0; extra == 'dev'
Requires-Dist: pytest>=7.4.0; extra == 'dev'
Requires-Dist: ruff; extra == 'dev'
